gdbundle_verilator_mem_if/__init__.py
gdbundle_verilator_mem_if/gdb_loader.py
gdbundle_verilator_mem_if-1.0.0.dist-info/LICENSE
gdbundle_verilator_mem_if-1.0.0.dist-info/METADATA
gdbundle_verilator_mem_if-1.0.0.dist-info/WHEEL
gdbundle_verilator_mem_if-1.0.0.dist-info/top_level.txt
gdbundle_verilator_mem_if-1.0.0.dist-info/RECORD
