Metadata-Version: 2.1
Name: gdbundle-verilator-mem-if
Version: 1.0.0
Summary: GDBundle plugin for the verilator_mem_if package.
License: MIT
Project-URL: homepage, https://github.com/idex-biometrics/gdbundle-verilator-mem-if
Requires-Python: >=3.6
License-File: LICENSE
Requires-Dist: gdbundle
